{"projects":[{"name":"base","path":["/"],"prefix":"/","store":"/base-app/store.js","main":{"js":["/base-app/static/js/2.6ed9947e.chunk.js","/base-app/main.js"],"css":["/base-app/static/css/main.f05016c4.css"]}},{"name":"sub1-app","path":["/sub1-app"],"prefix":"/sub1-app","store":"/sub-app1/store.js","main":{"js":["/sub-app1/static/js/0.8282568c.chunk.js","/sub-app1/static/js/3.713a2b83.chunk.js","/sub-app1/static/js/main.js?v=69320d8f","/sub-app1/static/js/store.js?v=5c39ee68"],"css":["/sub-app1/static/css/main.f05016c4.css"]}}]}